{
  "id": "2021.findings-acl.121",
  "title": "K-Adapter}: {I}nfusing {K}nowledge into {P}re-{T}rained {M}odels with {A}dapters",
  "authors": [
    "Wang, Ruize  and\nTang, Duyu  and\nDuan, Nan  and\nWei, Zhongyu  and\nHuang, Xuanjing  and\nJi, Jianshu  and\nCao, Guihong  and\nJiang, Daxin  and\nZhou, Ming"
  ],
  "year": "2021",
  "venue": "Findings of the Association for Computational Linguistics: ACL-IJCNLP 2021",
  "abstract": "Correct abstract if needed. Retain XML formatting tags such as <tex-math>.",
  "keywords": [
    "tex",
    "m",
    "k",
    "nowledge",
    "i",
    "re-",
    "p re- t",
    "xml",
    "tex-math",
    "correct",
    "dapters",
    "tags",
    "k nowledge",
    "math",
    "adapter"
  ],
  "url": "https://aclanthology.org/2021.findings-acl.121/",
  "provenance": {
    "collected_at": "2025-06-05 08:11:46",
    "source": "ACL Anthology",
    "version": "1.0"
  }
}