{
  "id": "2021.findings-acl.1",
  "title": "Explainable Inference Over Grounding-Abstract Chains for Science Questions",
  "authors": [
    "Thayaparan, Mokanarangan  and\nValentino, Marco  and\nFreitas, Andr{\\'e}"
  ],
  "year": "2021",
  "venue": "Findings of the Association for Computational Linguistics: ACL-IJCNLP 2021",
  "abstract": "Correct abstract if needed. Retain XML formatting tags such as <tex-math>.",
  "keywords": [
    "tex",
    "science",
    "science questions",
    "explainable",
    "grounding-abstract chains",
    "xml",
    "abstract",
    "chains",
    "questions",
    "tex-math",
    "inference",
    "correct",
    "explainable inference",
    "tags",
    "math"
  ],
  "url": "https://aclanthology.org/2021.findings-acl.1/",
  "provenance": {
    "collected_at": "2025-06-05 08:10:14",
    "source": "ACL Anthology",
    "version": "1.0"
  }
}