{
  "id": "2022.computel-1.22",
  "title": "Morphologically annotated corpora of Pomak",
  "authors": [
    "Jus{\\'u}f Karah{\\'o}ǧa, Ritv{\\'a}n  and\nKrimpas, Panagiotis G.  and\nStamou, Vivian  and\nArampatzakis, Vasileios  and\nKaramatskos, Dimitrios  and\nSevetlidis, Vasileios  and\nConstantinides, Nikolaos  and\nKokkas, Nikolaos  and\nPavlidis, George  and\nMarkantonatou, Stella"
  ],
  "year": "2022",
  "venue": "Proceedings of the Fifth Workshop on the Use of Computational Methods in the Study of Endangered Languages",
  "abstract": "The project XXXX is developing a platform to enable researchers of living languages to easily create and make available state-of-the-art spoken and textual annotated resources. As a case study we use Greek and Pomak, the latter being an endangered oral Slavic language of the Balkans (including Thrace/Greece). The linguistic documentation of Pomak is an ongoing work by an interdisciplinary team in close cooperation with the Pomak community of Greece. We describe our experience in the development of a Latin-based orthography and morphologically annotated text corpora of Pomak with state-of-the-art NLP technology. These resources will be made openly available on the XXXX site and the gold annotated corpora of Pomak will be made available on the Universal Dependencies treebank repository.",
  "keywords": [
    "work",
    "language",
    "nlp",
    "text",
    "dependencies",
    "we",
    "experience",
    "our experience",
    "the universal dependencies",
    "oral",
    "the gold",
    "the linguistic documentation",
    "balkans",
    "state",
    "thrace"
  ],
  "url": "https://aclanthology.org/2022.computel-1.22/",
  "provenance": {
    "collected_at": "2025-06-05 08:40:41",
    "source": "ACL Anthology",
    "version": "1.0"
  }
}