{
  "id": "2022.fl4nlp-1.0",
  "title": "Proceedings of the First Workshop on Federated Learning for Natural Language Processing (FL4NLP 2022)",
  "authors": [
    ""
  ],
  "year": "2022",
  "venue": "",
  "abstract": "Correct abstract if needed. Retain XML formatting tags such as <tex-math>.",
  "keywords": [
    "tex",
    "processing",
    "natural",
    "learning",
    "language",
    "fl4nlp",
    "workshop",
    "xml",
    "abstract",
    "tex-math",
    "correct",
    "proceedings",
    "tags",
    "math",
    "the first workshop"
  ],
  "url": "https://aclanthology.org/2022.fl4nlp-1.0/",
  "provenance": {
    "collected_at": "2025-06-05 08:42:38",
    "source": "ACL Anthology",
    "version": "1.0"
  }
}