{
  "id": "2022.bionlp-1.23",
  "title": "B}io{C}ite: A Deep Learning-based Citation Linkage Framework for Biomedical Research Articles",
  "authors": [
    "Singha Roy, Sudipta  and\nMercer, Robert E."
  ],
  "year": "2022",
  "venue": "Proceedings of the 21st Workshop on Biomedical Language Processing",
  "abstract": "Research papers reflect scientific advances. Citations are widely used in research publications to support the new findings and show their benefits, while also regulating the information flow to make the contents clearer for the audience. A citation in a research article refers to the information’s source, but not the specific text span from that source article. In biomedical research articles, this task is challenging as the same chemical or biological component can be represented in multiple ways in different papers from various domains. This paper suggests a mechanism for linking citing sentences in a publication with cited sentences in referenced sources. The framework presented here pairs the citing sentence with all of the sentences in the reference text, and then tries to retrieve the semantically equivalent pairs. These semantically related sentences from the reference paper are chosen as the cited statements. This effort involves designing a citation linkage framework utilizing sequential and tree-structured siamese deep learning models. This paper also provides a method to create a synthetic corpus for such a task.",
  "keywords": [
    "deep",
    "audience",
    "scientific advances",
    "all",
    "the audience",
    "information",
    "learning",
    "scientific",
    "text",
    "reference",
    "these semantically related sentences",
    "the semantically equivalent pairs",
    "the cited statements",
    "benefits",
    "a synthetic corpus"
  ],
  "url": "https://aclanthology.org/2022.bionlp-1.23/",
  "provenance": {
    "collected_at": "2025-06-05 08:39:51",
    "source": "ACL Anthology",
    "version": "1.0"
  }
}