{
  "id": "2024.lchange-1.10",
  "title": "Towards a Complete Solution to Lexical Semantic Change: an Extension to Multiple Time Periods and Diachronic Word Sense Induction",
  "authors": [
    "Periti, Francesco  and\nTahmasebi, Nina"
  ],
  "year": "2024",
  "venue": "Proceedings of the 5th Workshop on Computational Approaches to Historical Language Change",
  "abstract": "Correct abstract if needed. Retain XML formatting tags such as <tex-math>.",
  "keywords": [
    "lexical semantic change",
    "tex",
    "semantic",
    "word",
    "time",
    "induction",
    "sense",
    "change",
    "solution",
    "correct",
    "a complete solution",
    "lexical",
    "multiple time periods",
    "periods",
    "diachronic word sense induction"
  ],
  "url": "https://aclanthology.org/2024.lchange-1.10/",
  "provenance": {
    "collected_at": "2025-06-05 11:07:57",
    "source": "ACL Anthology",
    "version": "1.0"
  }
}