{
  "id": "P11-2007",
  "title": "The {A}rabic Online Commentary Dataset: an Annotated Dataset of Informal {A}rabic with High Dialectal Content",
  "authors": [
    "Zaidan, Omar F.  and\nCallison-Burch, Chris"
  ],
  "year": "2011",
  "venue": "Proceedings of the 49th Annual Meeting of the Association for Computational Linguistics: Human Language Technologies",
  "abstract": "Correct abstract if needed. Retain XML formatting tags such as <tex-math>.",
  "keywords": [
    "tex",
    "dialectal",
    "annotated",
    "an annotated dataset",
    "correct",
    "informal a rabic",
    "high",
    "content",
    "online",
    "dataset",
    "math",
    "formatting tags",
    "informal",
    "commentary",
    "xml"
  ],
  "url": "https://aclanthology.org/P11-2007/",
  "provenance": {
    "collected_at": "2025-06-04 23:03:08",
    "source": "ACL Anthology",
    "version": "1.0"
  }
}