{
  "id": "P13-3016",
  "title": "Detecting Chronic Critics Based on Sentiment Polarity and User{'}s Behavior in Social Media",
  "authors": [
    "Takase, Sho  and\nMurakami, Akiko  and\nEnoki, Miki  and\nOkazaki, Naoaki  and\nInui, Kentaro"
  ],
  "year": "2013",
  "venue": "51st Annual Meeting of the Association for Computational Linguistics Proceedings of the Student Research Workshop",
  "abstract": "Correct abstract if needed. Retain XML formatting tags such as <tex-math>.",
  "keywords": [
    "tex",
    "sentiment",
    "user",
    "media",
    "correct",
    "sentiment polarity",
    "behavior",
    "critics",
    "user s behavior",
    "math",
    "formatting tags",
    "social media",
    "xml",
    "chronic critics",
    "tex-math"
  ],
  "url": "https://aclanthology.org/P13-3016/",
  "provenance": {
    "collected_at": "2025-06-04 23:24:41",
    "source": "ACL Anthology",
    "version": "1.0"
  }
}