{
  "id": "P15-1174",
  "title": "Improving Evaluation of Machine Translation Quality Estimation",
  "authors": [
    "Graham, Yvette"
  ],
  "year": "2015",
  "venue": "Proceedings of the 53rd Annual Meeting of the Association for Computational Linguistics and the 7th International Joint Conference on Natural Language Processing (Volume 1: Long Papers)",
  "abstract": "Correct abstract if needed. Retain XML formatting tags such as <tex-math>.",
  "keywords": [
    "machine",
    "tex",
    "machine translation quality estimation",
    "translation",
    "evaluation",
    "quality",
    "estimation",
    "xml",
    "tex-math",
    "correct",
    "tags",
    "math",
    "formatting tags"
  ],
  "url": "https://aclanthology.org/P15-1174/",
  "provenance": {
    "collected_at": "2025-06-04 23:40:14",
    "source": "ACL Anthology",
    "version": "1.0"
  }
}