{
  "id": "P16-1049",
  "title": "D}oc{C}hat: An Information Retrieval Approach for Chatbot Engines Using Unstructured Documents",
  "authors": [
    "Yan, Zhao  and\nDuan, Nan  and\nBao, Junwei  and\nChen, Peng  and\nZhou, Ming  and\nLi, Zhoujun  and\nZhou, Jianshe"
  ],
  "year": "2016",
  "venue": "Proceedings of the 54th Annual Meeting of the Association for Computational Linguistics (Volume 1: Long Papers)",
  "abstract": "Correct abstract if needed. Retain XML formatting tags such as <tex-math>.",
  "keywords": [
    "information",
    "tex",
    "chatbot engines",
    "chatbot",
    "an information retrieval approach",
    "retrieval",
    "unstructured documents",
    "engines",
    "documents",
    "approach",
    "xml",
    "tex-math",
    "correct",
    "tags",
    "math"
  ],
  "url": "https://aclanthology.org/P16-1049/",
  "provenance": {
    "collected_at": "2025-06-04 23:46:55",
    "source": "ACL Anthology",
    "version": "1.0"
  }
}