{
  "id": "P16-2064",
  "title": "H}awkes Processes for Continuous Time Sequence Classification: an Application to Rumour Stance Classification in {T}witter",
  "authors": [
    "Lukasik, Michal  and\nSrijith, P. K.  and\nVu, Duy  and\nBontcheva, Kalina  and\nZubiaga, Arkaitz  and\nCohn, Trevor"
  ],
  "year": "2016",
  "venue": "Proceedings of the 54th Annual Meeting of the Association for Computational Linguistics (Volume 2: Short Papers)",
  "abstract": "Correct abstract if needed. Retain XML formatting tags such as <tex-math>.",
  "keywords": [
    "continuous time sequence classification",
    "h",
    "tex",
    "rumour stance classification",
    "sequence",
    "time",
    "classification",
    "continuous",
    "correct",
    "witter",
    "t witter",
    "rumour",
    "processes",
    "math",
    "formatting tags"
  ],
  "url": "https://aclanthology.org/P16-2064/",
  "provenance": {
    "collected_at": "2025-06-04 23:53:41",
    "source": "ACL Anthology",
    "version": "1.0"
  }
}