{
  "id": "W19-51",
  "title": "Proceedings of the Joint Workshop on Multiword Expressions and WordNet (MWE-WN 2019)",
  "authors": [
    ""
  ],
  "year": "2019",
  "venue": "",
  "abstract": "Correct abstract if needed. Retain XML formatting tags such as <tex-math>.",
  "keywords": [
    "tex",
    "wordnet mwe",
    "wordnet",
    "multiword expressions",
    "workshop",
    "the joint workshop",
    "xml",
    "mwe",
    "wn",
    "tex-math",
    "joint",
    "proceedings",
    "correct",
    "tags",
    "math"
  ],
  "url": "https://aclanthology.org/W19-5100/",
  "provenance": {
    "collected_at": "2025-06-05 01:01:59",
    "source": "ACL Anthology",
    "version": "1.0"
  }
}